pygore/__init__.py
pygore/internal.py
pygore/lib.py
pygore/libgore.dll
pygore/libgore.dylib
pygore/libgore.so
test/__init__.py
test/test_suite.py
pygore-0.5.0.dist-info/LICENSE
pygore-0.5.0.dist-info/METADATA
pygore-0.5.0.dist-info/WHEEL
pygore-0.5.0.dist-info/top_level.txt
pygore-0.5.0.dist-info/RECORD
