Metadata-Version: 2.1
Name: pygore
Version: 0.5.0
Summary: Python bindings for the Go Reverse Engineering Tool Kit
Home-page: https://github.com/goretk/pygore
Author: Go Reverse Engineering Tool Kit
License: UNKNOWN
Platform: UNKNOWN
Classifier: Programming Language :: Python :: 3
Classifier: License :: OSI Approved :: GNU Affero General Public License v3
Classifier: Development Status :: 4 - Beta
Classifier: Operating System :: POSIX :: Linux
Classifier: Operating System :: Microsoft :: Windows
Classifier: Operating System :: MacOS :: MacOS X
License-File: LICENSE
